bottles/__init__.py
bottles/ai.py
bottles/cli.py
bottles/editor.py
bottles_cli-0.2.0.dist-info/METADATA
bottles_cli-0.2.0.dist-info/WHEEL
bottles_cli-0.2.0.dist-info/entry_points.txt
bottles_cli-0.2.0.dist-info/top_level.txt
bottles_cli-0.2.0.dist-info/RECORD
