Metadata-Version: 2.1
Name: bottles-cli
Version: 0.2.0
Requires-Dist: Click
Requires-Dist: anthropic
